flagswift/__init__.py
flagswift/client.py
flagswift/exceptions.py
flagswift-1.1.3.dist-info/licenses/LICENSE
flagswift-1.1.3.dist-info/METADATA
flagswift-1.1.3.dist-info/WHEEL
flagswift-1.1.3.dist-info/top_level.txt
flagswift-1.1.3.dist-info/RECORD
